githubot/__init__.py
githubot/config.py
githubot/file.py
githubot/githubot.py
githubot/release.py
githubot-0.7.0.dist-info/LICENSE
githubot-0.7.0.dist-info/METADATA
githubot-0.7.0.dist-info/WHEEL
githubot-0.7.0.dist-info/entry_points.txt
githubot-0.7.0.dist-info/top_level.txt
githubot-0.7.0.dist-info/RECORD
