Metadata-Version: 2.1
Name: githubot
Version: 0.7.0
Summary: Command line tool to use Github API to automate some works.
Home-page: https://github.com/WqyJh/githubot
Author: wqy
Author-email: qiyingwangwqy@gmail.com
License: UNKNOWN
Keywords: github,ci
Platform: UNKNOWN
Classifier: Programming Language :: Python :: 3 :: Only
Requires-Dist: pygithub
Requires-Dist: docopt
